straitlets/compat.py
straitlets/builtin_models.py
straitlets/test_utils.py
straitlets/traits.py
straitlets/to_primitive.py
straitlets/serializable.py
straitlets/dispatch.py
straitlets/utils.py
straitlets/__init__.py
straitlets/tests/test_serializable.py
straitlets/tests/test_test_utils.py
straitlets/tests/conftest.py
straitlets/tests/test_examples.py
straitlets/tests/test_traits.py
straitlets/tests/test_to_primitive.py
straitlets/tests/test_utilities.py
straitlets/tests/test_compat.py
straitlets/tests/__init__.py
straitlets/tests/test_builtin_serializables.py
straitlets-0.2.3.dist-info/WHEEL
straitlets-0.2.3.dist-info/RECORD
straitlets-0.2.3.dist-info/top_level.txt
straitlets-0.2.3.dist-info/metadata.json
straitlets-0.2.3.dist-info/DESCRIPTION.rst
straitlets-0.2.3.dist-info/METADATA
straitlets-0.2.3.dist-info/zip-safe
