Metadata-Version: 2.0
Name: straitlets
Version: 0.2.3
Summary: Serializable IPython Traitlets
Home-page: https://github.com/quantopian/serializable-traitlets
Author: Quantopian Team
Author-email: opensource@quantopian.com
License: UNKNOWN
Platform: UNKNOWN
Classifier: Development Status :: 3 - Alpha
Classifier: Framework :: IPython
Classifier: Natural Language :: English
Classifier: Operating System :: OS Independent
Classifier: Programming Language :: Python :: 2.7
Classifier: Programming Language :: Python :: 3.4
Classifier: Programming Language :: Python
Requires-Dist: traitlets (>=4.1)
Requires-Dist: six (>=1.9.0)
Requires-Dist: pyyaml (>=3.11)
Requires-Dist: singledispatch (>=3.4.0)
Provides-Extra: test
Requires-Dist: tox; extra == 'test'
Requires-Dist: pytest (>=2.8.5); extra == 'test'
Requires-Dist: pytest-cov (>=1.8.1); extra == 'test'
Requires-Dist: pytest-pep8 (>=1.0.6); extra == 'test'
